knilb/__init__.py
knilb/__main__.py
knilb/agent.py
knilb/mock.ini
knilb/parser.py
tests/__init__.py
tests/test_agent.py
tests/test_parser.py
knilb-0.3.dist-info/LICENSE
knilb-0.3.dist-info/METADATA
knilb-0.3.dist-info/WHEEL
knilb-0.3.dist-info/entry_points.txt
knilb-0.3.dist-info/top_level.txt
knilb-0.3.dist-info/RECORD
