Metadata-Version: 2.1
Name: knilb
Version: 0.3
Summary: Example implementation of an Agent for Knilb
Home-page: http://knilb.com
Author: nko
Author-email: nate@knilb.com
License: MIT
Platform: UNKNOWN
Classifier: License :: OSI Approved :: MIT License
Classifier: Programming Language :: Python :: 2.7
Classifier: Programming Language :: Python :: 3.8
Requires-Dist: requests
Requires-Dist: responses
Requires-Dist: six
